ovhaitools/__init__.py
ovhaitools/extract.py
ovhaitools/ovhaitools.py
goatovhaitools-2024.7.16.1623.dist-info/METADATA
goatovhaitools-2024.7.16.1623.dist-info/WHEEL
goatovhaitools-2024.7.16.1623.dist-info/entry_points.txt
goatovhaitools-2024.7.16.1623.dist-info/top_level.txt
goatovhaitools-2024.7.16.1623.dist-info/RECORD
