Metadata-Version: 2.1
Name: goatovhaitools
Version: 2024.7.16.1623
Summary: OVHAI tools - CLI client for OVHAI
Author-email: Chris Stacks <centerupt@gmail.com>
Classifier: Programming Language :: Python :: 3
Classifier: Operating System :: OS Independent
Requires-Python: >=3.7
Requires-Dist: click >=8.0.4
Requires-Dist: requests-ntlm
